<?xml version="1.0" encoding="utf-8" ?><dwsync><file name="bottom.php" server="ftp.appmonkeys.ca/www/" local="3500064444" remote="318763443892975675" Dst="-1" /><file name="top.php" server="ftp.appmonkeys.ca/www/" local="3500064444" remote="318763443892975675" Dst="-1" /><file name="reg_form_post.php" server="ftp.appmonkeys.ca/www/" local="3500067840" remote="318763443892975675" Dst="-1" /><file name="add.php" server="ftp.appmonkeys.ca/www/" local="3500075950" remote="318763443892975675" Dst="-1" /><file name="sub.php" server="ftp.appmonkeys.ca/www/" local="3500076022" remote="318763443892975675" Dst="-1" /><file name="multi.php" server="ftp.appmonkeys.ca/www/" local="3500076628" remote="318763443892975675" Dst="-1" /><file name="nav.php" server="ftp.appmonkeys.ca/www/" local="3500073090" remote="318763443892975675" Dst="-1" /><file name="logout_request.php" server="ftp.appmonkeys.ca/www/" local="3500078620" remote="318763443892975675" Dst="-1" /><file name="login_request.php" server="ftp.appmonkeys.ca/www/" local="3500068952" remote="318763443892975675" Dst="-1" /></dwsync>